{"match":[{"jobID":"F2C8A6ED","foundMatches":5,"description":"wscript pack3","ruleName":"wscriptEvenMore","matchedRows":["0x105e:14:$1: WScript.Sleep(","0x10c7:14:$1: WScript.Sleep(","0x112c:14:$1: WScript.Sleep(","0x165f:14:$1: WScript.Sleep(","0x162e:5:$3: send("],"jobPath":"/malware/localhost_05-18_18-36-0047_F2C8A6ED/","totalScore":40},{"jobID":"F2C8A6ED","foundMatches":34,"description":"wscript elements","ruleName":"wscript","matchedRows":["0xa31:24:$1: ExpandEnvironmentStrings","0x9d6:13:$2: WScript.Shell","0x9fb:13:$2: WScript.Shell","0xa1f:13:$2: WScript.Shell","0x11a4:13:$2: WScript.Shell","0xa4b:4:$3: TEMP","0xa72:4:$3: Temp","0x10f3:4:$3: Temp","0x11d6:4:$3: Temp","0x134d:4:$3: Temp","0xa9f:14:$4: MSXML2.XMLHTTP","0xac5:14:$4: MSXML2.XMLHTTP","0xaea:14:$4: MSXML2.XMLHTTP","0xb3c:14:$4: MSXML2.XMLHTTP","0xb96:14:$4: MSXML2.XMLHTTP","0xbd3:14:$4: MSXML2.XMLHTTP","0xc2e:14:$4: MSXML2.XMLHTTP","0xc6d:14:$4: MSXML2.XMLHTTP","0xca2:14:$4: MSXML2.XMLHTTP","0xce8:14:$4: MSXML2.XMLHTTP","0xd43:14:$4: MSXML2.XMLHTTP","0xd80:14:$4: MSXML2.XMLHTTP","0xdbf:14:$4: MSXML2.XMLHTTP","0xe18:14:$4: MSXML2.XMLHTTP","0xe56:14:$4: MSXML2.XMLHTTP","0xf59:14:$4: MSXML2.XMLHTTP","0xf6c:17:$7: responsebody.get(","0xeb1:12:$8: ADODB.Stream","0x3be:8:$9: HTTP/404","0xccd:8:$9: HTTP/404","0xd14:8:$9: HTTP/404","0xf8c:8:$9: HTTP/404","0xfe0:8:$9: HTTP/404","0x114a:8:$9: HTTP/404"],"jobPath":"/malware/localhost_05-18_18-36-0047_F2C8A6ED/","totalScore":40},{"jobID":"F2C8A6ED","foundMatches":8,"description":"wscript pack2","ruleName":"wscriptMore","matchedRows":["0x1020:6:$1: Write(","0x11b6:4:$3: Run(","0x10cb:12:$4: .SaveToFile(","0xb4f:5:$6: open(","0xf09:5:$6: Open(","0x1103:4:$7: .exe","0x11e6:4:$7: .exe","0x135d:4:$7: .exe"],"jobPath":"/malware/localhost_05-18_18-36-0047_F2C8A6ED/","totalScore":40},{"jobID":"F2C8A6ED","foundMatches":8,"description":"wscript pack3","ruleName":"wscriptEvenMore","matchedRows":["0x955:14:$1: WScript.Sleep(","0x979:14:$1: WScript.Sleep(","0x99d:14:$1: WScript.Sleep(","0xc80:5:$3: send(","0xe2b:5:$3: send(","0x1103:4:$5: .exe","0x11e6:4:$5: .exe","0x135d:4:$5: .exe"],"jobPath":"/malware/localhost_05-18_18-36-0047_F2C8A6ED/","totalScore":40}]}